pyhtnorm-2.0.1.data/data/third_party_licenses/LICENSE-PCG32.txt
pyhtnorm-2.0.1.data/data/third_party_licenses/LICENSE-ZIGGURAT.txt
pyhtnorm-2.0.1.data/data/third_party_licenses/LICENSE-OPENBLAS.txt
pyhtnorm-2.0.1.dist-info/top_level.txt
pyhtnorm-2.0.1.dist-info/LICENSE
pyhtnorm-2.0.1.dist-info/RECORD
pyhtnorm-2.0.1.dist-info/METADATA
pyhtnorm-2.0.1.dist-info/WHEEL
pyhtnorm.libs/libopenblas-r0-f650aae0.3.3.so
pyhtnorm.libs/libblas-357956a1.so.3.4.2
pyhtnorm.libs/liblapack-1ad85175.so.3.4.2
pyhtnorm.libs/libquadmath-96973f99.so.0.0.0
pyhtnorm.libs/libgfortran-91cc3cb1.so.3.0.0
pyhtnorm/_htnorm.cpython-38-x86_64-linux-gnu.so
pyhtnorm/__init__.py
pyhtnorm/_version.py
