Metadata-Version: 2.1
Name: pyhtnorm
Version: 2.0.1
Summary: Fast Simulation of Hyperplane-Truncated Multivatiate Normal Distributions
Author-email: Zolisa Bleki <zolisa.bleki@gmail.com>
License: BSD 3-Clause License
Project-URL: source, https://github.com/zoj613/htnorm
Project-URL: tracker, https://github.com/zoj613/htnorm/issues
Keywords: statistical sampling,multivariate gaussian distribution,hyperplane truncated multivariate normal,structured precision multivariate normal,sampling distribution,posterior sampling
Classifier: Intended Audience :: Science/Research
Classifier: Topic :: Scientific/Engineering
Classifier: License :: OSI Approved :: BSD License
Classifier: Programming Language :: C
Classifier: Programming Language :: Python
Classifier: Programming Language :: Python :: 3 :: Only
Classifier: Operating System :: POSIX :: Linux
Classifier: Operating System :: Microsoft :: Windows :: Windows 10
Classifier: Operating System :: MacOS :: MacOS X
Classifier: Typing :: Typed
Requires-Python: >=3.8
License-File: LICENSE
Requires-Dist: numpy (>=1.19.0)
